[{"applicationId":"1175568","technologyGroups":{"Execute":{"3rd party":{},"Utilities":{},"Integration":{},"Serverless / FAAS":{},"Inversion of Control":{"CDI":1},"Rules & Processes":{},"Processing":{"Java EE JSON-P":1}},"Sustain":{"Logging":{},"Configuration Management":{},"Transactions":{"JTA":3},"Test":{},"Security":{},"Clustering":{},"Observability":{},"Resource Management":{}},"Connect":{"Binding":{"Java EE JAXB":1},"Streaming":{},"REST":{"JAX-RS":12},"WebService":{},"Messaging":{},"HTTP":{},"EJB":{"Stateless (SLSB)":4,"Message (MDB)":2,"Stateful (SFSB)":1},"Other":{"Properties":1,"Common Annotations":1}},"Store":{"Validation":{},"Persistence":{"Persistence units":1,"JPA XML":1,"JPA entities":4},"Database Driver":{},"Caching":{},"No SQL Database":{},"Database":{"JDBC XA datasources":1},"Object Mapping":{}},"View":{"Web":{"JSP Page":2,"Web XML File":1},"Markup":{"CSS":91,"JavaScript":1001,"HTML":363},"Rich":{},"MVC":{}}}}]